{
    "name": "bill_print_request",
    "plural": "Solicitudes",
    "singular": "Solicitud",
    "male": false,
    "alias": "req",
    "module": "bill",
    "fields": [{
            "id": "bill_print_request-id",
            "tblName": "bill_print_request",
            "name": "id",
            "label": null,
            "fk": false,
            "pk": true,
            "nullable": false,
            "type": "INTEGER",
            "format": null,
            "fkTblName": null,
            "emunOpts": null,
            "validations": []
        }, {
            "id": "bill_print_request-inst_id",
            "tblName": "bill_print_request",
            "name": "inst_id",
            "label": null,
            "fk": false,
            "pk": false,
            "nullable": false,
            "type": "INTEGER",
            "format": null,
            "fkTblName": null,
            "emunOpts": null,
            "validations": []
        }, {
            "id": "bill_print_request-bfile_id",
            "tblName": "bill_print_request",
            "name": "bfile_id",
            "label": null,
            "fk": false,
            "pk": false,
            "nullable": true,
            "type": "INTEGER",
            "format": null,
            "fkTblName": null,
            "emunOpts": null,
            "validations": []
        }, {
            "id": "bill_print_request-emp_id",
            "tblName": "bill_print_request",
            "name": "emp_id",
            "label": null,
            "fk": false,
            "pk": false,
            "nullable": false,
            "type": "INTEGER",
            "format": null,
            "fkTblName": null,
            "emunOpts": null,
            "validations": []
        }, {
            "id": "bill_print_request-beg_dt",
            "tblName": "bill_print_request",
            "name": "beg_dt",
            "label": null,
            "fk": false,
            "pk": false,
            "nullable": false,
            "type": "DATE_TIME",
            "format": "TYPE_DD_MM_YYYY_HH12_MM_A",
            "fkTblName": null,
            "emunOpts": null,
            "validations": []
        }, {
            "id": "bill_print_request-end_dt",
            "tblName": "bill_print_request",
            "name": "end_dt",
            "label": null,
            "fk": false,
            "pk": false,
            "nullable": true,
            "type": "DATE_TIME",
            "format": "TYPE_DD_MM_YYYY_HH12_MM_A",
            "fkTblName": null,
            "emunOpts": null,
            "validations": []
        }, {
            "id": "bill_print_request-requested_bills",
            "tblName": "bill_print_request",
            "name": "requested_bills",
            "label": null,
            "fk": false,
            "pk": false,
            "nullable": false,
            "type": "INTEGER",
            "format": "TYPE_INTEGER",
            "fkTblName": null,
            "emunOpts": null,
            "validations": []
        }, {
            "id": "bill_print_request-msg",
            "tblName": "bill_print_request",
            "name": "msg",
            "label": null,
            "fk": false,
            "pk": false,
            "nullable": true,
            "type": "LONG_TEXT",
            "format": "TYPE_TEXT",
            "fkTblName": null,
            "emunOpts": null,
            "validations": [{
                    "type": "MAX",
                    "len": 1024,
                    "mask": null
                }]
        }, {
            "id": "bill_print_request-error_msg",
            "tblName": "bill_print_request",
            "name": "error_msg",
            "label": null,
            "fk": false,
            "pk": false,
            "nullable": true,
            "type": "LONG_TEXT",
            "format": "TYPE_TEXT",
            "fkTblName": null,
            "emunOpts": null,
            "validations": [{
                    "type": "MAX",
                    "len": 1024,
                    "mask": null
                }]
        }, {
            "id": "bill_print_request-error_trace",
            "tblName": "bill_print_request",
            "name": "error_trace",
            "label": null,
            "fk": false,
            "pk": false,
            "nullable": true,
            "type": "LONG_TEXT",
            "format": "TYPE_TEXT",
            "fkTblName": null,
            "emunOpts": null,
            "validations": [{
                    "type": "MAX",
                    "len": 5120,
                    "mask": null
                }]
        }, {
            "id": "bill_print_request-status",
            "tblName": "bill_print_request",
            "name": "status",
            "label": null,
            "fk": false,
            "pk": false,
            "nullable": true,
            "type": "ENUM",
            "format": "TYPE_ENUM",
            "fkTblName": null,
            "emunOpts": [["running", null], ["testing", null], ["fail", null], ["ready", null], ["downloaded", null]],
            "validations": []
        }, {
            "id": "bill_print_request-rate",
            "tblName": "bill_print_request",
            "name": "rate",
            "label": null,
            "fk": false,
            "pk": false,
            "nullable": true,
            "type": "INTEGER",
            "format": "TYPE_INTEGER",
            "fkTblName": null,
            "emunOpts": null,
            "validations": []
        }, {
            "id": "bill_print_request-file_len_kb",
            "tblName": "bill_print_request",
            "name": "file_len_kb",
            "label": null,
            "fk": false,
            "pk": false,
            "nullable": true,
            "type": "INTEGER",
            "format": "TYPE_INTEGER",
            "fkTblName": null,
            "emunOpts": null,
            "validations": []
        }],
    "toStrFldIds": [],
    "grids": [{
            "name": "main",
            "label": null,
            "type": "MASTER_TABLE",
            "tbls": [{
                    "tblName": "bill_print_request",
                    "fldId": null,
                    "conds": null,
                    "type": null
                }],
            "flds": [],
            "conds": [],
            "orderByFlds": [],
            "accs": [{
                    "global": false,
                    "name": null,
                    "label": null,
                    "type": "EXPORT",
                    "tableName": null,
                    "gridName": null,
                    "newFormName": null,
                    "editFormName": null,
                    "deskIcon": null,
                    "webIcon": null,
                    "enumRouteKeyPos": null,
                    "enumRouteFldId": null,
                    "additionalAction": false,
                    "apiEndPoint": null,
                    "apiResponse": null,
                    "apiConfirmDialog": null,
                    "apiReload": null,
                    "apiMethod": null,
                    "apiRowIndex": null,
                    "opts": []
                }, {
                    "global": false,
                    "name": null,
                    "label": null,
                    "type": "LOGS",
                    "tableName": null,
                    "gridName": null,
                    "newFormName": null,
                    "editFormName": null,
                    "deskIcon": null,
                    "webIcon": null,
                    "enumRouteKeyPos": null,
                    "enumRouteFldId": null,
                    "additionalAction": false,
                    "apiEndPoint": null,
                    "apiResponse": null,
                    "apiConfirmDialog": null,
                    "apiReload": null,
                    "apiMethod": null,
                    "apiRowIndex": null,
                    "opts": []
                }, {
                    "global": false,
                    "name": null,
                    "label": null,
                    "type": "SPACE",
                    "tableName": null,
                    "gridName": null,
                    "newFormName": null,
                    "editFormName": null,
                    "deskIcon": null,
                    "webIcon": null,
                    "enumRouteKeyPos": null,
                    "enumRouteFldId": null,
                    "additionalAction": false,
                    "apiEndPoint": null,
                    "apiResponse": null,
                    "apiConfirmDialog": null,
                    "apiReload": null,
                    "apiMethod": null,
                    "apiRowIndex": null,
                    "opts": []
                }, {
                    "global": false,
                    "name": null,
                    "label": null,
                    "type": "ADD",
                    "tableName": null,
                    "gridName": null,
                    "newFormName": null,
                    "editFormName": null,
                    "deskIcon": null,
                    "webIcon": null,
                    "enumRouteKeyPos": null,
                    "enumRouteFldId": null,
                    "additionalAction": false,
                    "apiEndPoint": null,
                    "apiResponse": null,
                    "apiConfirmDialog": null,
                    "apiReload": null,
                    "apiMethod": null,
                    "apiRowIndex": null,
                    "opts": []
                }, {
                    "global": false,
                    "name": null,
                    "label": null,
                    "type": "EDIT",
                    "tableName": null,
                    "gridName": null,
                    "newFormName": null,
                    "editFormName": null,
                    "deskIcon": null,
                    "webIcon": null,
                    "enumRouteKeyPos": null,
                    "enumRouteFldId": null,
                    "additionalAction": false,
                    "apiEndPoint": null,
                    "apiResponse": null,
                    "apiConfirmDialog": null,
                    "apiReload": null,
                    "apiMethod": null,
                    "apiRowIndex": null,
                    "opts": []
                }, {
                    "global": false,
                    "name": null,
                    "label": null,
                    "type": "REMOVE",
                    "tableName": null,
                    "gridName": null,
                    "newFormName": null,
                    "editFormName": null,
                    "deskIcon": null,
                    "webIcon": null,
                    "enumRouteKeyPos": null,
                    "enumRouteFldId": null,
                    "additionalAction": false,
                    "apiEndPoint": null,
                    "apiResponse": null,
                    "apiConfirmDialog": null,
                    "apiReload": null,
                    "apiMethod": null,
                    "apiRowIndex": null,
                    "opts": []
                }],
            "grpFldIds": [],
            "tblName": "bill_print_request",
            "testRequest": null,
            "testEmployeeId": null,
            "sortAscById": null,
            "sortDescById": null,
            "sortable": true,
            "dataPath": null,
            "deletePath": null
        }],
    "groups": [],
    "forms": [{
            "name": "main",
            "tblName": "bill_print_request",
            "tabs": [{
                    "name": "main",
                    "label": "main",
                    "flds": []
                }],
            "insertPath": null,
            "updatePath": null,
            "selectPath": null,
            "customNewTitle": null,
            "customEditTitle": null,
            "table": null
        }],
    "uniques": [],
    "billing": false,
    "activeFldId": null
}