{
    "name": "bill_station",
    "plural": "Estaciones y Tanques",
    "singular": "Estaci\u00F3n o Tanque",
    "male": false,
    "alias": "e",
    "module": "bill",
    "fields": [{
            "id": "bill_station-id",
            "tblName": "bill_station",
            "name": "id",
            "label": null,
            "fk": false,
            "pk": true,
            "nullable": false,
            "type": "INTEGER",
            "format": null,
            "fkTblName": null,
            "emunOpts": null,
            "validations": []
        }, {
            "id": "bill_station-inst_id",
            "tblName": "bill_station",
            "name": "inst_id",
            "label": null,
            "fk": true,
            "pk": false,
            "nullable": false,
            "type": "INTEGER",
            "format": null,
            "fkTblName": "bill_instance",
            "emunOpts": null,
            "validations": []
        }, {
            "id": "bill_station-lat",
            "tblName": "bill_station",
            "name": "lat",
            "label": "Latitud",
            "fk": false,
            "pk": false,
            "nullable": false,
            "type": "BIG_DECIMAL",
            "format": "TYPE_DECIMAL_2",
            "fkTblName": null,
            "emunOpts": null,
            "validations": []
        }, {
            "id": "bill_station-lon",
            "tblName": "bill_station",
            "name": "lon",
            "label": "Longitud",
            "fk": false,
            "pk": false,
            "nullable": false,
            "type": "BIG_DECIMAL",
            "format": "TYPE_DECIMAL_2",
            "fkTblName": null,
            "emunOpts": null,
            "validations": []
        }, {
            "id": "bill_station-alt",
            "tblName": "bill_station",
            "name": "alt",
            "label": "Altitud",
            "fk": false,
            "pk": false,
            "nullable": false,
            "type": "BIG_DECIMAL",
            "format": "TYPE_DECIMAL_2",
            "fkTblName": null,
            "emunOpts": null,
            "validations": []
        }, {
            "id": "bill_station-type",
            "tblName": "bill_station",
            "name": "type",
            "label": "Tipo",
            "fk": false,
            "pk": false,
            "nullable": false,
            "type": "ENUM",
            "format": "TYPE_ENUM",
            "fkTblName": null,
            "emunOpts": [["erp", "Estaci\u00F3n Reguladora de Presi\u00F3n"], ["erpc", "Estaci\u00F3n Reguladora de Presi\u00F3n de Ciudad"], ["tnq", "Tanque de Almacenamiento"]],
            "validations": []
        }, {
            "id": "bill_station-code",
            "tblName": "bill_station",
            "name": "code",
            "label": "C\u00F3digo",
            "fk": false,
            "pk": false,
            "nullable": false,
            "type": "TEXT",
            "format": "TYPE_TEXT",
            "fkTblName": null,
            "emunOpts": null,
            "validations": [{
                    "type": "UNIQUE",
                    "len": null,
                    "mask": null
                }, {
                    "type": "MAX",
                    "len": 50,
                    "mask": null
                }]
        }, {
            "id": "bill_station-beg_date",
            "tblName": "bill_station",
            "name": "beg_date",
            "label": "Entrada en Operaci\u00F3n",
            "fk": false,
            "pk": false,
            "nullable": false,
            "type": "DATE",
            "format": "TYPE_DD_MM_YYYY",
            "fkTblName": null,
            "emunOpts": null,
            "validations": []
        }, {
            "id": "bill_station-capacity",
            "tblName": "bill_station",
            "name": "capacity",
            "label": "Capacidad",
            "fk": false,
            "pk": false,
            "nullable": true,
            "type": "INTEGER",
            "format": "TYPE_INTEGER",
            "fkTblName": null,
            "emunOpts": null,
            "validations": []
        }, {
            "id": "bill_station-cod_cert",
            "tblName": "bill_station",
            "name": "cod_cert",
            "label": "C\u00F3digo certificado",
            "fk": false,
            "pk": false,
            "nullable": true,
            "type": "TEXT",
            "format": "TYPE_TEXT",
            "fkTblName": null,
            "emunOpts": null,
            "validations": []
        },  {
            "id": "bill_station-inspector_id",
            "tblName": "bill_station",
            "name": "inspector_id",
            "label": "Organismo",
            "fk": true,
            "pk": false,
            "nullable": true,
            "type": "INTEGER",
            "format": null,
            "fkTblName": "bill_inst_inspector",
            "emunOpts": null,
            "validations": []
        }],
    "toStrFldIds": [],
    "grids": [{
            "name": "main",
            "label": null,
            "type": "MASTER_TABLE",
            "tbls": [{
                    "tblName": "bill_station",
                    "fldId": null,
                    "conds": null,
                    "type": null
                }, {
                    "tblName": "bill_instance",
                    "fldId": "bill_station-inst_id",
                    "conds": null,
                    "type": null
                }, {
                    "tblName": "dane_poblado",
                    "fldId": "bill_instance-pob_id",
                    "conds": null,
                    "type": null
                }],
            "flds": [{
                    "fldId": "bill_station-id",
                    "label": null,
                    "format": null,
                    "width": null,
                    "oper": null,
                    "align": null,
                    "showZero": false,
                    "editable": false,
                    "isKey": true,
                    "toString": false
                }, {
                    "fldId": "dane_poblado-name",
                    "label": "Poblado",
                    "format": null,
                    "width": 50,
                    "oper": null,
                    "align": null,
                    "showZero": false,
                    "editable": false,
                    "isKey": false,
                    "toString": true
                }, {
                    "fldId": "bill_instance-name",
                    "label": "Instacia",
                    "format": null,
                    "width": 50,
                    "oper": null,
                    "align": null,
                    "showZero": false,
                    "editable": false,
                    "isKey": false,
                    "toString": true
                }, {
                    "fldId": "bill_station-type",
                    "label": null,
                    "format": null,
                    "width": 50,
                    "oper": null,
                    "align": null,
                    "showZero": false,
                    "editable": false,
                    "isKey": false,
                    "toString": false
                }, {
                    "fldId": "dane_poblado-code",
                    "label": "C\u00F3digo",
                    "format": null,
                    "width": 50,
                    "oper": null,
                    "align": null,
                    "showZero": false,
                    "editable": false,
                    "isKey": false,
                    "toString": false
                }],
            "conds": [],
            "orderByFlds": [],
            "accs": [{
                    "global": false,
                    "name": null,
                    "label": null,
                    "type": "EXPORT",
                    "tableName": null,
                    "gridName": null,
                    "newFormName": null,
                    "editFormName": null,
                    "deskIcon": null,
                    "webIcon": null,
                    "enumRouteKeyPos": null,
                    "enumRouteFldId": null,
                    "additionalAction": false,
                    "apiEndPoint": null,
                    "apiResponse": null,
                    "apiConfirmDialog": null,
                    "apiReload": null,
                    "apiMethod": null,
                    "apiRowIndex": null,
                    "opts": []
                }, {
                    "global": false,
                    "name": null,
                    "label": null,
                    "type": "LOGS",
                    "tableName": null,
                    "gridName": null,
                    "newFormName": null,
                    "editFormName": null,
                    "deskIcon": null,
                    "webIcon": null,
                    "enumRouteKeyPos": null,
                    "enumRouteFldId": null,
                    "additionalAction": false,
                    "apiEndPoint": null,
                    "apiResponse": null,
                    "apiConfirmDialog": null,
                    "apiReload": null,
                    "apiMethod": null,
                    "apiRowIndex": null,
                    "opts": []
                }, {
                    "global": false,
                    "name": null,
                    "label": null,
                    "type": "SPACE",
                    "tableName": null,
                    "gridName": null,
                    "newFormName": null,
                    "editFormName": null,
                    "deskIcon": null,
                    "webIcon": null,
                    "enumRouteKeyPos": null,
                    "enumRouteFldId": null,
                    "additionalAction": false,
                    "apiEndPoint": null,
                    "apiResponse": null,
                    "apiConfirmDialog": null,
                    "apiReload": null,
                    "apiMethod": null,
                    "apiRowIndex": null,
                    "opts": []
                }, {
                    "global": false,
                    "name": null,
                    "label": null,
                    "type": "ADD",
                    "tableName": null,
                    "gridName": null,
                    "newFormName": null,
                    "editFormName": null,
                    "deskIcon": null,
                    "webIcon": null,
                    "enumRouteKeyPos": null,
                    "enumRouteFldId": null,
                    "additionalAction": false,
                    "apiEndPoint": null,
                    "apiResponse": null,
                    "apiConfirmDialog": null,
                    "apiReload": null,
                    "apiMethod": null,
                    "apiRowIndex": null,
                    "opts": []
                }, {
                    "global": false,
                    "name": null,
                    "label": null,
                    "type": "EDIT",
                    "tableName": null,
                    "gridName": null,
                    "newFormName": null,
                    "editFormName": null,
                    "deskIcon": null,
                    "webIcon": null,
                    "enumRouteKeyPos": null,
                    "enumRouteFldId": null,
                    "additionalAction": false,
                    "apiEndPoint": null,
                    "apiResponse": null,
                    "apiConfirmDialog": null,
                    "apiReload": null,
                    "apiMethod": null,
                    "apiRowIndex": null,
                    "opts": []
                }, {
                    "global": false,
                    "name": null,
                    "label": null,
                    "type": "REMOVE",
                    "tableName": null,
                    "gridName": null,
                    "newFormName": null,
                    "editFormName": null,
                    "deskIcon": null,
                    "webIcon": null,
                    "enumRouteKeyPos": null,
                    "enumRouteFldId": null,
                    "additionalAction": false,
                    "apiEndPoint": null,
                    "apiResponse": null,
                    "apiConfirmDialog": null,
                    "apiReload": null,
                    "apiMethod": null,
                    "apiRowIndex": null,
                    "opts": []
                }],
            "grpFldIds": [],
            "tblName": "bill_station",
            "testRequest": null,
            "testEmployeeId": null,
            "sortAscById": null,
            "sortDescById": null,
            "sortable": true,
            "dataPath": null,
            "deletePath": null
        }],
    "groups": [],
    "forms": [{
            "name": "main",
            "tblName": "bill_station",
            "tabs": [{
                    "name": "main",
                    "label": "main",
                    "flds": [{
                            "fldId": "bill_station-inst_id",
                            "required": true,
                            "readFromParent": false,
                            "slotNum": null,
                            "cmbParentFldId": null,
                            "cmbGrid": "combo_net",
                            "editable": true,
                            "fixedEnum": null,
                            "fixedBoolean": null,
                            "titleCase": null
                        }, {
                            "fldId": "bill_station-code",
                            "required": true,
                            "readFromParent": null,
                            "slotNum": null,
                            "cmbParentFldId": null,
                            "cmbGrid": null,
                            "editable": true,
                            "fixedEnum": null,
                            "fixedBoolean": null,
                            "titleCase": true
                        }, {
                            "fldId": "bill_station-type",
                            "required": true,
                            "readFromParent": null,
                            "slotNum": null,
                            "cmbParentFldId": null,
                            "cmbGrid": null,
                            "editable": true,
                            "fixedEnum": null,
                            "fixedBoolean": null,
                            "titleCase": null
                        }, {
                            "fldId": "bill_station-capacity",
                            "required": true,
                            "readFromParent": null,
                            "slotNum": null,
                            "cmbParentFldId": null,
                            "cmbGrid": null,
                            "editable": true,
                            "fixedEnum": null,
                            "fixedBoolean": null,
                            "titleCase": null
                        }, {
                            "fldId": "bill_station-cod_cert",
                            "required": true,
                            "readFromParent": null,
                            "slotNum": null,
                            "cmbParentFldId": null,
                            "cmbGrid": null,
                            "editable": true,
                            "fixedEnum": null,
                            "fixedBoolean": null,
                            "titleCase": null
                        }, {
                            "fldId": "bill_station-inspector_id",
                            "required": true,
                            "readFromParent": null,
                            "slotNum": null,
                            "cmbParentFldId": null,
                            "cmbGrid": "cmb",
                            "editable": true,
                            "fixedEnum": null,
                            "fixedBoolean": null,
                            "titleCase": null
                        }, {
                            "fldId": "bill_station-lat",
                            "required": true,
                            "readFromParent": null,
                            "slotNum": null,
                            "cmbParentFldId": null,
                            "cmbGrid": null,
                            "editable": true,
                            "fixedEnum": null,
                            "fixedBoolean": null,
                            "titleCase": null
                        }, {
                            "fldId": "bill_station-lon",
                            "required": true,
                            "readFromParent": null,
                            "slotNum": null,
                            "cmbParentFldId": null,
                            "cmbGrid": null,
                            "editable": true,
                            "fixedEnum": null,
                            "fixedBoolean": null,
                            "titleCase": null
                        }, {
                            "fldId": "bill_station-alt",
                            "required": true,
                            "readFromParent": null,
                            "slotNum": null,
                            "cmbParentFldId": null,
                            "cmbGrid": null,
                            "editable": true,
                            "fixedEnum": null,
                            "fixedBoolean": null,
                            "titleCase": null
                        }, {
                            "fldId": "bill_station-beg_date",
                            "required": true,
                            "readFromParent": null,
                            "slotNum": null,
                            "cmbParentFldId": null,
                            "cmbGrid": null,
                            "editable": true,
                            "fixedEnum": null,
                            "fixedBoolean": null,
                            "titleCase": null
                        }]
                }],
            "insertPath": null,
            "updatePath": null,
            "selectPath": null,
            "customNewTitle": null,
            "customEditTitle": null,
            "table": null
        }],
    "uniques": [],
    "billing": false,
    "activeFldId": null
}