{
    "name": "menu",
    "plural": "Menus",
    "singular": "Menu",
    "male": true,
    "alias": "m",
    "module": "sys",
    "fields": [{
            "id": "menu-id",
            "tblName": "menu",
            "name": "id",
            "label": "M\u00F3dulo",
            "fk": false,
            "pk": true,
            "nullable": false,
            "type": "INTEGER",
            "format": "TYPE_INTEGER",
            "fkTblName": "menu",
            "emunOpts": null,
            "validations": []
        }, {
            "id": "menu-label",
            "tblName": "menu",
            "name": "label",
            "label": null,
            "fk": false,
            "pk": false,
            "nullable": false,
            "type": "LONG_TEXT",
            "format": "TYPE_TEXT",
            "fkTblName": null,
            "emunOpts": null,
            "validations": [{
                    "type": "MAX",
                    "len": 256,
                    "mask": null
                }]
        }, {
            "id": "menu-className",
            "tblName": "menu",
            "name": "className",
            "label": null,
            "fk": false,
            "pk": false,
            "nullable": true,
            "type": "LONG_TEXT",
            "format": "TYPE_TEXT",
            "fkTblName": null,
            "emunOpts": null,
            "validations": [{
                    "type": "MAX",
                    "len": 256,
                    "mask": null
                }]
        }, {
            "id": "menu-place",
            "tblName": "menu",
            "name": "place",
            "label": null,
            "fk": false,
            "pk": false,
            "nullable": false,
            "type": "INTEGER",
            "format": "TYPE_INTEGER",
            "fkTblName": null,
            "emunOpts": null,
            "validations": []
        }, {
            "id": "menu-icon_path",
            "tblName": "menu",
            "name": "icon_path",
            "label": null,
            "fk": false,
            "pk": false,
            "nullable": true,
            "type": "TEXT",
            "format": "TYPE_TEXT",
            "fkTblName": null,
            "emunOpts": null,
            "validations": [{
                    "type": "MAX",
                    "len": 128,
                    "mask": null
                }]
        }, {
            "id": "menu-web_path",
            "tblName": "menu",
            "name": "web_path",
            "label": null,
            "fk": false,
            "pk": false,
            "nullable": true,
            "type": "LONG_TEXT",
            "format": "TYPE_TEXT",
            "fkTblName": null,
            "emunOpts": null,
            "validations": [{
                    "type": "MAX",
                    "len": 256,
                    "mask": null
                }]
        }, {
            "id": "menu-web_icon",
            "tblName": "menu",
            "name": "web_icon",
            "label": null,
            "fk": false,
            "pk": false,
            "nullable": true,
            "type": "TEXT",
            "format": "TYPE_TEXT",
            "fkTblName": null,
            "emunOpts": null,
            "validations": [{
                    "type": "MAX",
                    "len": 128,
                    "mask": null
                }]
        }, {
            "id": "menu-reg_type",
            "tblName": "menu",
            "name": "reg_type",
            "label": null,
            "fk": false,
            "pk": false,
            "nullable": true,
            "type": "ENUM",
            "format": "TYPE_ENUM",
            "fkTblName": null,
            "emunOpts": [["mod", null], ["bar", null], ["opt", null], ["sub", null], ["sopt", null], ["panel", null], ["popt", null]],
            "validations": []
        }, {
            "id": "menu-sup_id",
            "tblName": "menu",
            "name": "sup_id",
            "label": null,
            "fk": false,
            "pk": false,
            "nullable": true,
            "type": "INTEGER",
            "format": null,
            "fkTblName": null,
            "emunOpts": null,
            "validations": []
        }, {
            "id": "menu-cache",
            "tblName": "menu",
            "name": "cache",
            "label": null,
            "fk": false,
            "pk": false,
            "nullable": true,
            "type": "LONG_TEXT",
            "format": "TYPE_TEXT",
            "fkTblName": null,
            "emunOpts": null,
            "validations": [{
                    "type": "MAX",
                    "len": 1024,
                    "mask": null
                }]
        }, {
            "id": "menu-has_short_name",
            "tblName": "menu",
            "name": "has_short_name",
            "label": null,
            "fk": false,
            "pk": false,
            "nullable": true,
            "type": "BOOLEAN",
            "format": "TYPE_BOOLEAN",
            "fkTblName": null,
            "emunOpts": null,
            "validations": []
        }, {
            "id": "menu-locked",
            "tblName": "menu",
            "name": "locked",
            "label": null,
            "fk": false,
            "pk": false,
            "nullable": false,
            "type": "BOOLEAN",
            "format": "TYPE_BOOLEAN",
            "fkTblName": null,
            "emunOpts": null,
            "validations": []
        }, {
            "id": "menu-color",
            "tblName": "menu",
            "name": "color",
            "label": null,
            "fk": false,
            "pk": false,
            "nullable": true,
            "type": "INTEGER",
            "format": "TYPE_INTEGER",
            "fkTblName": null,
            "emunOpts": null,
            "validations": []
        }, {
            "id": "menu-mod_cfg_class",
            "tblName": "menu",
            "name": "mod_cfg_class",
            "label": null,
            "fk": false,
            "pk": false,
            "nullable": true,
            "type": "TEXT",
            "format": "TYPE_TEXT",
            "fkTblName": null,
            "emunOpts": null,
            "validations": [{
                    "type": "MAX",
                    "len": 128,
                    "mask": null
                }]
        }, {
            "id": "menu-prof_cfg_class",
            "tblName": "menu",
            "name": "prof_cfg_class",
            "label": null,
            "fk": false,
            "pk": false,
            "nullable": true,
            "type": "TEXT",
            "format": "TYPE_TEXT",
            "fkTblName": null,
            "emunOpts": null,
            "validations": [{
                    "type": "MAX",
                    "len": 128,
                    "mask": null
                }]
        }, {
            "id": "menu-frm_prof_class",
            "tblName": "menu",
            "name": "frm_prof_class",
            "label": null,
            "fk": false,
            "pk": false,
            "nullable": true,
            "type": "TEXT",
            "format": "TYPE_TEXT",
            "fkTblName": null,
            "emunOpts": null,
            "validations": [{
                    "type": "MAX",
                    "len": 128,
                    "mask": null
                }]
        }, {
            "id": "menu-frm_mod_class",
            "tblName": "menu",
            "name": "frm_mod_class",
            "label": null,
            "fk": false,
            "pk": false,
            "nullable": true,
            "type": "TEXT",
            "format": "TYPE_TEXT",
            "fkTblName": null,
            "emunOpts": null,
            "validations": [{
                    "type": "MAX",
                    "len": 128,
                    "mask": null
                }]
        }, {
            "id": "menu-pnl_class",
            "tblName": "menu",
            "name": "pnl_class",
            "label": null,
            "fk": false,
            "pk": false,
            "nullable": true,
            "type": "TEXT",
            "format": "TYPE_TEXT",
            "fkTblName": null,
            "emunOpts": null,
            "validations": [{
                    "type": "MAX",
                    "len": 128,
                    "mask": null
                }]
        }, {
            "id": "menu-frm_auth_desk_class",
            "tblName": "menu",
            "name": "frm_auth_desk_class",
            "label": null,
            "fk": false,
            "pk": false,
            "nullable": true,
            "type": "TEXT",
            "format": "TYPE_TEXT",
            "fkTblName": null,
            "emunOpts": null,
            "validations": [{
                    "type": "MAX",
                    "len": 128,
                    "mask": null
                }]
        }, {
            "id": "menu-frm_auth_mobile_class",
            "tblName": "menu",
            "name": "frm_auth_mobile_class",
            "label": null,
            "fk": false,
            "pk": false,
            "nullable": true,
            "type": "TEXT",
            "format": "TYPE_TEXT",
            "fkTblName": null,
            "emunOpts": null,
            "validations": [{
                    "type": "MAX",
                    "len": 128,
                    "mask": null
                }]
        }, {
            "id": "menu-crud_type",
            "tblName": "menu",
            "name": "crud_type",
            "label": null,
            "fk": false,
            "pk": false,
            "nullable": true,
            "type": "ENUM",
            "format": "TYPE_ENUM",
            "fkTblName": null,
            "emunOpts": [["grid", null], ["group", null]],
            "validations": []
        }, {
            "id": "menu-crud_tbl_name",
            "tblName": "menu",
            "name": "crud_tbl_name",
            "label": null,
            "fk": false,
            "pk": false,
            "nullable": true,
            "type": "TEXT",
            "format": "TYPE_TEXT",
            "fkTblName": null,
            "emunOpts": null,
            "validations": [{
                    "type": "MAX",
                    "len": 128,
                    "mask": null
                }]
        }, {
            "id": "menu-crud_grid_name",
            "tblName": "menu",
            "name": "crud_grid_name",
            "label": null,
            "fk": false,
            "pk": false,
            "nullable": true,
            "type": "TEXT",
            "format": "TYPE_TEXT",
            "fkTblName": null,
            "emunOpts": null,
            "validations": [{
                    "type": "MAX",
                    "len": 128,
                    "mask": null
                }]
        }],
    "toStrFldIds": [],
    "grids": [{
            "name": "main",
            "label": null,
            "type": "MASTER_TABLE",
            "tbls": [{
                    "tblName": "menu",
                    "fldId": null,
                    "conds": null,
                    "type": null
                }],
            "flds": [{
                    "fldId": "menu-id",
                    "label": null,
                    "format": null,
                    "width": null,
                    "oper": null,
                    "align": null,
                    "showZero": false,
                    "editable": false,
                    "isKey": true,
                    "toString": false
                }],
            "conds": [],
            "orderByFlds": [],
            "accs": [{
                    "global": false,
                    "name": null,
                    "label": null,
                    "type": "EXPORT",
                    "tableName": null,
                    "gridName": null,
                    "newFormName": null,
                    "editFormName": null,
                    "deskIcon": null,
                    "webIcon": null,
                    "enumRouteKeyPos": null,
                    "enumRouteFldId": null,
                    "additionalAction": false,
                    "apiEndPoint": null,
                    "apiResponse": null,
                    "apiConfirmDialog": null,
                    "apiReload": null,
                    "apiMethod": null,
                    "apiRowIndex": null,
                    "opts": []
                }, {
                    "global": false,
                    "name": null,
                    "label": null,
                    "type": "LOGS",
                    "tableName": null,
                    "gridName": null,
                    "newFormName": null,
                    "editFormName": null,
                    "deskIcon": null,
                    "webIcon": null,
                    "enumRouteKeyPos": null,
                    "enumRouteFldId": null,
                    "additionalAction": false,
                    "apiEndPoint": null,
                    "apiResponse": null,
                    "apiConfirmDialog": null,
                    "apiReload": null,
                    "apiMethod": null,
                    "apiRowIndex": null,
                    "opts": []
                }, {
                    "global": false,
                    "name": null,
                    "label": null,
                    "type": "SPACE",
                    "tableName": null,
                    "gridName": null,
                    "newFormName": null,
                    "editFormName": null,
                    "deskIcon": null,
                    "webIcon": null,
                    "enumRouteKeyPos": null,
                    "enumRouteFldId": null,
                    "additionalAction": false,
                    "apiEndPoint": null,
                    "apiResponse": null,
                    "apiConfirmDialog": null,
                    "apiReload": null,
                    "apiMethod": null,
                    "apiRowIndex": null,
                    "opts": []
                }, {
                    "global": false,
                    "name": null,
                    "label": null,
                    "type": "ADD",
                    "tableName": null,
                    "gridName": null,
                    "newFormName": null,
                    "editFormName": null,
                    "deskIcon": null,
                    "webIcon": null,
                    "enumRouteKeyPos": null,
                    "enumRouteFldId": null,
                    "additionalAction": false,
                    "apiEndPoint": null,
                    "apiResponse": null,
                    "apiConfirmDialog": null,
                    "apiReload": null,
                    "apiMethod": null,
                    "apiRowIndex": null,
                    "opts": []
                }, {
                    "global": false,
                    "name": null,
                    "label": null,
                    "type": "EDIT",
                    "tableName": null,
                    "gridName": null,
                    "newFormName": null,
                    "editFormName": null,
                    "deskIcon": null,
                    "webIcon": null,
                    "enumRouteKeyPos": null,
                    "enumRouteFldId": null,
                    "additionalAction": false,
                    "apiEndPoint": null,
                    "apiResponse": null,
                    "apiConfirmDialog": null,
                    "apiReload": null,
                    "apiMethod": null,
                    "apiRowIndex": null,
                    "opts": []
                }, {
                    "global": false,
                    "name": null,
                    "label": null,
                    "type": "REMOVE",
                    "tableName": null,
                    "gridName": null,
                    "newFormName": null,
                    "editFormName": null,
                    "deskIcon": null,
                    "webIcon": null,
                    "enumRouteKeyPos": null,
                    "enumRouteFldId": null,
                    "additionalAction": false,
                    "apiEndPoint": null,
                    "apiResponse": null,
                    "apiConfirmDialog": null,
                    "apiReload": null,
                    "apiMethod": null,
                    "apiRowIndex": null,
                    "opts": []
                }],
            "grpFldIds": [],
            "tblName": "menu",
            "testRequest": {
                "tableName": "menu",
                "gridName": "main",
                "profileId": null,
                "ints": [],
                "dates": [],
                "bools": [],
                "strings": []
            },
            "testEmployeeId": null,
            "sortAscById": null,
            "sortDescById": null,
            "sortable": true,
            "dataPath": null,
            "deletePath": null
        }, {
            "name": "all_modules",
            "label": "",
            "type": "COMBO",
            "tbls": [{
                    "tblName": "menu",
                    "fldId": null,
                    "conds": null,
                    "type": null
                }],
            "flds": [{
                    "fldId": "menu-id",
                    "label": null,
                    "format": null,
                    "width": null,
                    "oper": null,
                    "align": null,
                    "showZero": false,
                    "editable": false,
                    "isKey": true,
                    "toString": false
                }, {
                    "fldId": "menu-label",
                    "label": "M\u00F3dulo",
                    "format": null,
                    "width": 50,
                    "oper": null,
                    "align": null,
                    "showZero": false,
                    "editable": false,
                    "isKey": false,
                    "toString": true
                }],
            "conds": [{
                    "fldId": "menu-reg_type",
                    "comparison": "FIXED",
                    "slotType": null,
                    "slot": null,
                    "readFromParentId": false,
                    "readFromTextFilter": false,
                    "readFromFilter": false,
                    "cmbGridName": null,
                    "fixedEnum": "mod",
                    "fixedInt": null,
                    "permissionChecker": null
                }],
            "orderByFlds": [],
            "accs": null,
            "grpFldIds": [],
            "tblName": "menu",
            "testRequest": {
                "tableName": "menu",
                "gridName": "all_modules",
                "profileId": null,
                "ints": [],
                "dates": [],
                "bools": [],
                "strings": []
            },
            "testEmployeeId": null,
            "sortAscById": null,
            "sortDescById": null,
            "sortable": false,
            "dataPath": "",
            "deletePath": ""
        }],
    "groups": [],
    "forms": [{
            "name": "main",
            "tblName": "menu",
            "tabs": [{
                    "name": "main",
                    "label": "main",
                    "flds": [{
                            "fldId": "menu-label",
                            "required": true,
                            "readFromParent": null,
                            "slotNum": null,
                            "cmbParentFldId": null,
                            "cmbGrid": null,
                            "editable": true,
                            "fixedEnum": null,
                            "fixedBoolean": null,
                            "titleCase": null
                        }, {
                            "fldId": "menu-className",
                            "required": false,
                            "readFromParent": null,
                            "slotNum": null,
                            "cmbParentFldId": null,
                            "cmbGrid": null,
                            "editable": true,
                            "fixedEnum": null,
                            "fixedBoolean": null,
                            "titleCase": null
                        }, {
                            "fldId": "menu-place",
                            "required": true,
                            "readFromParent": null,
                            "slotNum": null,
                            "cmbParentFldId": null,
                            "cmbGrid": null,
                            "editable": true,
                            "fixedEnum": null,
                            "fixedBoolean": null,
                            "titleCase": null
                        }, {
                            "fldId": "menu-icon_path",
                            "required": false,
                            "readFromParent": null,
                            "slotNum": null,
                            "cmbParentFldId": null,
                            "cmbGrid": null,
                            "editable": true,
                            "fixedEnum": null,
                            "fixedBoolean": null,
                            "titleCase": true
                        }, {
                            "fldId": "menu-web_path",
                            "required": false,
                            "readFromParent": null,
                            "slotNum": null,
                            "cmbParentFldId": null,
                            "cmbGrid": null,
                            "editable": true,
                            "fixedEnum": null,
                            "fixedBoolean": null,
                            "titleCase": null
                        }, {
                            "fldId": "menu-web_icon",
                            "required": false,
                            "readFromParent": null,
                            "slotNum": null,
                            "cmbParentFldId": null,
                            "cmbGrid": null,
                            "editable": true,
                            "fixedEnum": null,
                            "fixedBoolean": null,
                            "titleCase": true
                        }, {
                            "fldId": "menu-reg_type",
                            "required": false,
                            "readFromParent": null,
                            "slotNum": null,
                            "cmbParentFldId": null,
                            "cmbGrid": null,
                            "editable": true,
                            "fixedEnum": null,
                            "fixedBoolean": null,
                            "titleCase": null
                        }, {
                            "fldId": "menu-sup_id",
                            "required": false,
                            "readFromParent": null,
                            "slotNum": null,
                            "cmbParentFldId": null,
                            "cmbGrid": null,
                            "editable": true,
                            "fixedEnum": null,
                            "fixedBoolean": null,
                            "titleCase": null
                        }, {
                            "fldId": "menu-cache",
                            "required": false,
                            "readFromParent": null,
                            "slotNum": null,
                            "cmbParentFldId": null,
                            "cmbGrid": null,
                            "editable": true,
                            "fixedEnum": null,
                            "fixedBoolean": null,
                            "titleCase": null
                        }, {
                            "fldId": "menu-has_short_name",
                            "required": false,
                            "readFromParent": null,
                            "slotNum": null,
                            "cmbParentFldId": null,
                            "cmbGrid": null,
                            "editable": true,
                            "fixedEnum": null,
                            "fixedBoolean": null,
                            "titleCase": null
                        }, {
                            "fldId": "menu-locked",
                            "required": true,
                            "readFromParent": null,
                            "slotNum": null,
                            "cmbParentFldId": null,
                            "cmbGrid": null,
                            "editable": true,
                            "fixedEnum": null,
                            "fixedBoolean": null,
                            "titleCase": null
                        }, {
                            "fldId": "menu-color",
                            "required": false,
                            "readFromParent": null,
                            "slotNum": null,
                            "cmbParentFldId": null,
                            "cmbGrid": null,
                            "editable": true,
                            "fixedEnum": null,
                            "fixedBoolean": null,
                            "titleCase": null
                        }, {
                            "fldId": "menu-mod_cfg_class",
                            "required": false,
                            "readFromParent": null,
                            "slotNum": null,
                            "cmbParentFldId": null,
                            "cmbGrid": null,
                            "editable": true,
                            "fixedEnum": null,
                            "fixedBoolean": null,
                            "titleCase": true
                        }, {
                            "fldId": "menu-prof_cfg_class",
                            "required": false,
                            "readFromParent": null,
                            "slotNum": null,
                            "cmbParentFldId": null,
                            "cmbGrid": null,
                            "editable": true,
                            "fixedEnum": null,
                            "fixedBoolean": null,
                            "titleCase": true
                        }, {
                            "fldId": "menu-frm_prof_class",
                            "required": false,
                            "readFromParent": null,
                            "slotNum": null,
                            "cmbParentFldId": null,
                            "cmbGrid": null,
                            "editable": true,
                            "fixedEnum": null,
                            "fixedBoolean": null,
                            "titleCase": true
                        }, {
                            "fldId": "menu-frm_mod_class",
                            "required": false,
                            "readFromParent": null,
                            "slotNum": null,
                            "cmbParentFldId": null,
                            "cmbGrid": null,
                            "editable": true,
                            "fixedEnum": null,
                            "fixedBoolean": null,
                            "titleCase": true
                        }, {
                            "fldId": "menu-pnl_class",
                            "required": false,
                            "readFromParent": null,
                            "slotNum": null,
                            "cmbParentFldId": null,
                            "cmbGrid": null,
                            "editable": true,
                            "fixedEnum": null,
                            "fixedBoolean": null,
                            "titleCase": true
                        }, {
                            "fldId": "menu-frm_auth_desk_class",
                            "required": false,
                            "readFromParent": null,
                            "slotNum": null,
                            "cmbParentFldId": null,
                            "cmbGrid": null,
                            "editable": true,
                            "fixedEnum": null,
                            "fixedBoolean": null,
                            "titleCase": true
                        }, {
                            "fldId": "menu-frm_auth_mobile_class",
                            "required": false,
                            "readFromParent": null,
                            "slotNum": null,
                            "cmbParentFldId": null,
                            "cmbGrid": null,
                            "editable": true,
                            "fixedEnum": null,
                            "fixedBoolean": null,
                            "titleCase": true
                        }, {
                            "fldId": "menu-crud_type",
                            "required": false,
                            "readFromParent": null,
                            "slotNum": null,
                            "cmbParentFldId": null,
                            "cmbGrid": null,
                            "editable": true,
                            "fixedEnum": null,
                            "fixedBoolean": null,
                            "titleCase": null
                        }, {
                            "fldId": "menu-crud_tbl_name",
                            "required": false,
                            "readFromParent": null,
                            "slotNum": null,
                            "cmbParentFldId": null,
                            "cmbGrid": null,
                            "editable": true,
                            "fixedEnum": null,
                            "fixedBoolean": null,
                            "titleCase": true
                        }, {
                            "fldId": "menu-crud_grid_name",
                            "required": false,
                            "readFromParent": null,
                            "slotNum": null,
                            "cmbParentFldId": null,
                            "cmbGrid": null,
                            "editable": true,
                            "fixedEnum": null,
                            "fixedBoolean": null,
                            "titleCase": true
                        }]
                }],
            "insertPath": null,
            "updatePath": null,
            "selectPath": null,
            "customNewTitle": null,
            "customEditTitle": null,
            "table": null
        }],
    "uniques": [],
    "billing": false,
    "activeFldId": null
}